{
  "name": "Nimbus",
  "version": "0.0.3",
  "storage": "aws",
  "description": "Loyalty xNFT for your Web3 journey",
  "longDescription": "Tracking your portfolio on multiple platforms, optimize your earnings while enjoying our perk",
  "tag": "defi",
  "website": "https://getnimbus.io",
  "kind": "app",
  "icon": {
    "md": "./assets/icon.png"
  },
  "contact": "@thanhle27",
  "screenshots": [
    "./assets/1.png",
    "./assets/2.png",
    "./assets/3.png",
    "./assets/4.png"
  ],
  "entrypoints": {
    "default": {
      "web": "./web-build/index.html"
    }
  }
}